fkpackage/__init__.py
fkpackage/addition.py
fkpackage/subtraction.py
fkpackage/extras/__init__.py
fkpackage/extras/division.py
fkpackage/extras/multiplication.py
fkpackage-0.0.4.dist-info/METADATA
fkpackage-0.0.4.dist-info/WHEEL
fkpackage-0.0.4.dist-info/top_level.txt
fkpackage-0.0.4.dist-info/RECORD
